{
  "gid": "501689772772687877",
  "clan_steamid": "103582791433224455",
  "event_name": "뱀의 매력",
  "event_type": 13,
  "appid": 570,
  "server_address": null,
  "server_password": null,
  "rtime32_start_time": 1738181280,
  "rtime32_end_time": 1738186201,
  "comment_count": 0,
  "creator_steamid": "0",
  "last_update_steamid": "0",
  "event_notes": "see announcement body",
  "jsondata": {
    "localized_subtitle": [],
    "localized_summary": [],
    "localized_title_image": [],
    "localized_capsule_image": [
      "0fbfa0c9307a74e3b6e785421e71a13df72093f1.png"
    ],
    "bSaleEnabled": false,
    "sale_show_creator": false,
    "sale_sections": [],
    "sale_browsemore_text": "",
    "sale_browsemore_url": "",
    "sale_browsemore_color": "",
    "sale_browsemore_bgcolor": "",
    "localized_sale_header": [],
    "localized_sale_overlay": [],
    "localized_sale_product_banner": [],
    "localized_sale_product_mobile_banner": [],
    "localized_sale_logo": [],
    "sale_font": "",
    "sale_background_color": "",
    "sale_header_offset": 530,
    "referenced_appids": [],
    "bBroadcastEnabled": false,
    "broadcastChatSetting": "hide",
    "default_broadcast_title": "#Broadcast_default_title_dev",
    "localized_broadcast_title": [],
    "localized_broadcast_left_image": [],
    "localized_broadcast_right_image": [],
    "broadcast_whitelist": [],
    "bScheduleEnabled": false,
    "scheduleEntries": [],
    "automatically_push_updated_source": true,
    "valve_access_log": [
      {
        "strSteamID": "76561198042665686",
        "rtUpdated": 1738110811
      },
      {
        "strSteamID": "76561198166130601",
        "rtUpdated": 1738183474
      },
      {
        "strSteamID": "76561197978027217",
        "rtUpdated": 1738181316
      }
    ]
  },
  "announcement_body": {
    "gid": "501689772772687878",
    "clanid": "3703047",
    "posterid": "0",
    "headline": "뱀의 매력",
    "posttime": 1738181317,
    "updatetime": 1738183474,
    "body": [
      "[img]{STEAM_CLAN_IMAGE}/3703047/0fbfa0c9307a74e3b6e785421e71a13df72093f1.png[/img]",
      "생물학자라면 누구나 이렇게 말할 겁니다. 뱀은 매혹적인 생물체라고. 뱀은 뼈대가 없습니다. 뱀은 뇌나 장기가 없습니다. 뱀은 튜브처럼 생긴 근육 하나로 몸 전체와 입, 두 눈, 배설부가 구성되어 있습니다. 그렇습니다. 동물이라면 그렇게 적은 신체 부위로 살아 있을 수 없기 마련입니다만, 어째서인지 뱀은 이 모든 난관을 극복하고 어떻게든 살아 나갑니다. ",
      "이쯤에서 저희는 이 모든 사항과 관련하여 연락했던 생물학자가 사실은 전화에 응답한 적이 없었으며, 그렇기에 이전 문단에서 밝힌 몇 가지 세부 사항은 추측으로 작성해야 했다는 사실을 고백해야겠습니다. 하지만 솔직히 말해서, 뱀이 근사하다는 사실은 굳이 지루한 뱀 전문가를 찾아서 들을 필요는 없습니다. 뱀은 방어구에도, 무기에도, 몸에도, 심지어 몸에도 잘 어울립니다. 이미 근사한 것인데, 거기에 뱀을 잔뜩 더하면 실제로 폭발할 수도 있으므로 조심해야 합니다.",
      "짐작하셨겠지만, 새로운 '뱀의 매력' 보물을 자랑스럽게 선보입니다. 보물에는 여러분이 좋아하시는 영웅 주위에서 스르르 미끄러지듯 돌아다니며 비늘 스타일로 멋지게 감싸줄 커뮤니티 제작 아이템 세트 9가지가 담겨 있습니다. 뱀의 해를 맞이하며 설날에 딱 맞는 보물이 아닐 수 없습니다.",
      "보물 하나를 열 때마다, 스냅파이어, 메두사, 그림자 주술사, 나가 세이렌, 레이저, 대지령, 암살 기사를 위한 뱀 스타일 세트 한 가지가 제공됩니다. 아울러, 일정 확률로 희귀한 리치 세트나 매우 희귀한 강령사제 세트를 획득할 수도 있습니다. '뱀의 매력' 보물을 2.49달러로 직접 구매하여 설날 기분을 만끽하고 매끈한 치장의 즐거움을 누려보시기 바랍니다."
    ],
    "commentcount": 200,
    "tags": [
      "mod_reviewed",
      "ModAct_873083815_1738182173_0",
      "ModAct_873083815_1738184751_4"
    ],
    "language": 4,
    "hidden": 0,
    "forum_topic_id": "598517164755961810",
    "event_gid": "501689772772687877",
    "voteupcount": 477,
    "votedowncount": 266,
    "ban_check_result": 0,
    "banned": 0
  },
  "published": 1,
  "hidden": 0,
  "rtime32_visibility_start": 0,
  "rtime32_visibility_end": 0,
  "broadcaster_accountid": 0,
  "follower_count": 0,
  "ignore_count": 0,
  "forum_topic_id": "598517164755961810",
  "rtime32_last_modified": 1738199605,
  "news_post_gid": "0",
  "rtime_mod_reviewed": 1738184752,
  "featured_app_tagid": 0,
  "referenced_appids": [],
  "build_id": 0,
  "build_branch": "",
  "unlisted": 0,
  "votes_up": 477,
  "votes_down": 266,
  "comment_type": "ForumTopic",
  "gidfeature": "1636418037459185108",
  "gidfeature2": "598517164755961810",
  "clan_steamid_original": "103582791433224455"
}