{
  "gid": "512986184073347348",
  "clan_steamid": "103582791433224455",
  "event_name": "Gameplaypatch 7.41",
  "event_type": 14,
  "appid": 570,
  "server_address": null,
  "server_password": null,
  "rtime32_start_time": 1774395780,
  "rtime32_end_time": 1774400401,
  "comment_count": 0,
  "creator_steamid": "0",
  "last_update_steamid": "0",
  "event_notes": "see announcement body",
  "jsondata": {
    "localized_subtitle": [],
    "localized_summary": [],
    "localized_title_image": [],
    "localized_capsule_image": [
      "b51c728ac0c7a28973be12fce11a3c869037177d.png"
    ],
    "bSaleEnabled": false,
    "sale_show_creator": false,
    "sale_sections": [],
    "sale_browsemore_text": "",
    "sale_browsemore_url": "",
    "sale_browsemore_color": "",
    "sale_browsemore_bgcolor": "",
    "localized_sale_header": [],
    "localized_sale_overlay": [],
    "localized_sale_product_banner": [],
    "localized_sale_product_mobile_banner": [],
    "localized_sale_logo": [],
    "sale_font": "",
    "sale_background_color": "",
    "sale_header_offset": 530,
    "referenced_appids": [],
    "bBroadcastEnabled": false,
    "broadcastChatSetting": "hide",
    "default_broadcast_title": "#Broadcast_default_title_dev",
    "localized_broadcast_title": [],
    "localized_broadcast_left_image": [],
    "localized_broadcast_right_image": [],
    "broadcast_whitelist": [],
    "bScheduleEnabled": false,
    "scheduleEntries": [],
    "valve_access_log": [
      {
        "strSteamID": "76561199370270521",
        "rtUpdated": 1774286313
      },
      {
        "strSteamID": "76561199113010392",
        "rtUpdated": 1774030078
      },
      {
        "strSteamID": "76561198166130601",
        "rtUpdated": 1774470190
      },
      {
        "strSteamID": "76561197978027217",
        "rtUpdated": 1774395823
      }
    ],
    "automatically_push_updated_source": true,
    "rt_migrated_time": 1774470088.078
  },
  "announcement_body": {
    "gid": "512986184073347349",
    "clanid": "3703047",
    "posterid": "0",
    "headline": "Gameplaypatch 7.41",
    "posttime": 1774395824,
    "updatetime": 1774470190,
    "body": [
      "[p]Gameplaypatch 7.41 is nu uit. Bekijk de nieuwste wijzigingen [url=\"https://www.dota2.com/patches/7.41\"]hier[/url].",
      "Bovendien hebben we de volgende verbeteringen en bugfixes doorgevoerd:",
      "[/p][list][*][p] Indicator boven het hoofd toegevoegd voor wanneer een verbruiksartikel op een bondgenoot wordt gebruikt of aan een bondgenoot wordt gegeven binnen 1200 eenheden (bijv. Tango).[/p][/*][*][p] Optie toegevoegd aan de instellingen om het huidige zicht van je held te tonen als de sneltoets 'Held selecteren' wordt ingedrukt. Wordt beïnvloed door oorlogsmist.[/p][/*][*][p] Benodigdheden voor itemrecepten worden vanaf nu altijd gekocht op volgorde van prijs, van hoog naar laag, om 'snel kopen' voorspelbaarder te maken (met uitzondering van onder andere laarzen en Blink Dagger).[/p][/*][*][p] Probleem verholpen waarbij bepaalde treffereffecten niet altijd naar behoren werkten als er meer dan 256 projectielen tegelijkertijd door de lucht vlogen.[/p][/*][*][p] Probleem verholpen waarbij de Observer en Sentry Wards van spelers onder bepaalde omstandigheden werden vervangen door een foutmodel. [/p][/*][*][p] Als je een neutraal item wilt maken met een volle inventaris en het vak voor het neutrale item al een uniek item van een held bevat (bijv. Gris-Gris van de Witch Doctor), wordt het item niet langer automatisch verbruikt. In plaats daarvan mislukt het maken.[/p][/*][*][p] Probleem verholpen waarbij de sneltoetsen voor het maken van neutrale items de gewone sneltoetsen overschreven als je klikte op de knop om een neutraal item te maken van een held die je niet bestuurde.[/p][/*][*][p] Vaardigheidsselectie:[/p][list][*][p] Alle helden beschikken nu over hun gave als ze worden gekozen. [/p][/*][*][p] Beschikbare vaardigheden bijgewerkt op basis van de vaardigheden die in update 7.41 zijn toegevoegd/verwijderd.[/p][/*][*][p] Probleem verholpen waarbij de Spirit Bear van de Lone Druid na een tijdje niet verscheen.[/p][/*][*][p] Probleem verholpen waarbij Keen Conveyance niet werd verleend door Rearm.[/p][/*][*][p] Probleem verholpen waarbij Reactive Tazer van Techies niet werkte met Aghanim's Shard van Largo.[/p][/*][/list][/*][*][p]Ondersteuning beëindigd voor GPU's die DirectX 11/SM5 niet ondersteunen. Voor toekomstige grafische functies en prestatieverbeteringen is DX11/SM5 vereist. Een toekomstige update verwijdert de ondersteuning voor oudere apparaten. (99,96% van de actieve spelers heeft apparaten die DX11/SM5 ondersteunen.) [/p][/*][/list]"
    ],
    "commentcount": 606,
    "tags": [
      "mod_reviewed",
      "ModAct_487176015_1774397331_0",
      "mod_require_rereview"
    ],
    "language": 14,
    "hidden": 0,
    "forum_topic_id": "807972525953850193",
    "event_gid": "512986184073347348",
    "voteupcount": 4172,
    "votedowncount": 1160,
    "ban_check_result": 0,
    "banned": 0
  },
  "published": 1,
  "hidden": 0,
  "rtime32_visibility_start": 0,
  "rtime32_visibility_end": 0,
  "broadcaster_accountid": 0,
  "follower_count": 1,
  "ignore_count": 0,
  "forum_topic_id": "807972525953850193",
  "rtime32_last_modified": 1774470190,
  "news_post_gid": "0",
  "rtime_mod_reviewed": 1774397331,
  "featured_app_tagid": 0,
  "referenced_appids": [],
  "build_id": 0,
  "build_branch": "",
  "unlisted": 0,
  "votes_up": 4162,
  "votes_down": 1159,
  "comment_type": "ForumTopic",
  "gidfeature": "1636418037459185108",
  "gidfeature2": "807972525953850193",
  "clan_steamid_original": "103582791433224455"
}