{
  "gid": "4442331835939160455",
  "clan_steamid": "103582791433224455",
  "event_name": "Atualização do Dota 2 — 12 de novembro de 2024",
  "event_type": 12,
  "appid": 570,
  "server_address": null,
  "server_password": null,
  "rtime32_start_time": 1731457500,
  "rtime32_end_time": 1731461401,
  "comment_count": 0,
  "creator_steamid": "0",
  "last_update_steamid": "0",
  "event_notes": "see announcement body",
  "jsondata": {
    "localized_subtitle": [],
    "localized_summary": [],
    "localized_title_image": [],
    "localized_capsule_image": [],
    "bSaleEnabled": false,
    "sale_show_creator": false,
    "sale_sections": [],
    "sale_browsemore_text": "",
    "sale_browsemore_url": "",
    "sale_browsemore_color": "",
    "sale_browsemore_bgcolor": "",
    "localized_sale_header": [],
    "localized_sale_overlay": [],
    "localized_sale_product_banner": [],
    "localized_sale_product_mobile_banner": [],
    "localized_sale_logo": [],
    "sale_font": "",
    "sale_background_color": "",
    "sale_header_offset": 530,
    "referenced_appids": [],
    "bBroadcastEnabled": false,
    "broadcastChatSetting": "hide",
    "default_broadcast_title": "#Broadcast_default_title_dev",
    "localized_broadcast_title": [],
    "localized_broadcast_left_image": [],
    "localized_broadcast_right_image": [],
    "broadcast_whitelist": [],
    "bScheduleEnabled": false,
    "scheduleEntries": [],
    "valve_access_log": [
      {
        "strSteamID": "76561197978027217",
        "rtUpdated": 1731457530
      },
      {
        "strSteamID": "76561199547417290",
        "rtUpdated": 1731448834
      },
      {
        "strSteamID": "76561198093408953",
        "rtUpdated": 1731521128
      }
    ],
    "clone_from_event_gid": "4442331835939160312",
    "clone_from_sale_enabled": false,
    "automatically_push_updated_source": true
  },
  "announcement_body": {
    "gid": "4442331835939160456",
    "clanid": "3703047",
    "posterid": "0",
    "headline": "Atualização do Dota 2 — 12 de novembro de 2024",
    "posttime": 1731457534,
    "updatetime": 1731521128,
    "body": [
      "[b]Kez:[/b]",
      "[list]",
      "[*] Katana dos Kazurai: redução do dano por segundo (7/8/9/10% → 6/7/8/9%)",
      "[*] Avanço Falcoado: aumento da taxa base de ataque com a Katana (1,3/1,2/1,1/1,0 → 1,4/1,3/1,2/1,1)",
      "[*] Avanço Falcoado: redução da duração (7s → 3/4/5/6s)",
      "[*] Dança do Raptor: aumento do intervalo entre usos (40/32/24s → 40/35/30s)",
      "[*] Véu do Corvo: aumento do intervalo entre usos (40/32/24s → 40/35/30s)",
      "[*] Garra de Rapina: correção da corrente, que não era quebrada quando vinculada a um alvo fora do alcance",
      "Sai dos Shodo: correção de algumas interações com a marca, que estavam causando dano além do esperado",
      "[*] Garra de Rapina: correção de problema que a fazia ignorar esquivas",
      "[*] Corte Ecoante: correção de problema que a fazia ignorar esquivas",
      "[*] Corte Ecoante: correção de problema que permitia matar entregadores",
      "[*] Corte Ecoante: correção de problema que permitia a Kez escapar de habilidades com acorrentamento ou impedimento de movimento (como o Campo Cinético do Disruptor)",
      "[/list]",
      "Desde o lançamento do 4º Ato da Queda Coronal e de Kez, também corrigimos vários problemas:",
      "[list]",
      "[*] Fragmento Lunar: correção de travamento do cliente",
      "[*] Totem da Morsa Ogro: correção de travamento do servidor envolvendo o Lone Druid",
      "[*] Correção de vários problemas com a compra rápida",
      "[*] Correção dos estilos alternativos destraváveis dos Arcanos de Shen e Dragonus, que não estavam sendo aplicados aos respectivos pacotes de cursores",
      "[*] Juggernaut: correção do estilo alternativo da Espreita Primal",
      "[*] Correção de diversos travamentos em encontros do 4º Ato",
      "[*] Agora, vencer partidas no modo Seleção de Habilidades concede duas fichas e oito sucatas, em vez de três fichas e duas sucatas",
      "[*] Campo Spleenado: adição de seção de pontuação ao menu principal para exibir informações de pontuação Correção do resumo da pontuação, que não era exibido após vencer as cinco fases",
      "[*] Campo Spleenado: correção da última fase, que não concedia o adicional de 4.000 pontos quando concluída",
      "[*] Carnificina Castelã: correção do Tunelador, cujas partículas estavam sem modelo, e problemas com o rebatimento de granadas",
      "[*] Carnificina Castelã: correção de alguns terrenos invisíveis que bloqueavam disparos",
      "[*] Spoon Man: correção de problema em que o cursor do mouse ficava invisível quando janelas eram abertas",
      "[*] Spoon Man: correção de travamento quando um botão era pressionado antes do carregamento do jogo",
      "[*] Spoon Man: correção de problema que permitia ficar preso dentro de um bloco",
      "[*] Poleiro de Espinhos: correção de problema eventual com o recebimento de recompensas",
      "[*] Poleiro de Espinhos: correção de problema eventual com o salvamento da quantidade de ouro",
      "[*] Correção do encontro com o Guarda Real Cego, que não estava funcionando",
      "[*] Correção das pinturas do 4º Ato, que não estavam aparecendo na roda de mensagens",
      "[*] Agora, clicar em alertas de fichas recebidas como presente no mapa da Queda Coronal abrem o encontro associado",
      "[*] Correção de problema em que, ao reproduzir a animação de estreia de Kez, o cliente do jogo podia ficar com uma tela preta",
      "[*] Correção dos novos troféus da Queda Coronal, que não estavam sendo exibidos",
      "[/list]"
    ],
    "commentcount": 105,
    "tags": [
      "patchnotes",
      "mod_reviewed",
      "ModAct_1519738978_1731457701_0",
      "mod_require_rereview"
    ],
    "language": 22,
    "hidden": 0,
    "forum_topic_id": "4633735454895638461",
    "event_gid": "4442331835939160455",
    "voteupcount": 658,
    "votedowncount": 134,
    "ban_check_result": 0,
    "banned": 0
  },
  "published": 1,
  "hidden": 0,
  "rtime32_visibility_start": 0,
  "rtime32_visibility_end": 0,
  "broadcaster_accountid": 0,
  "follower_count": 0,
  "ignore_count": 0,
  "forum_topic_id": "4633735454895638461",
  "rtime32_last_modified": 1731521128,
  "news_post_gid": "0",
  "rtime_mod_reviewed": 1731457701,
  "featured_app_tagid": 0,
  "referenced_appids": [],
  "build_id": 0,
  "build_branch": "",
  "unlisted": 0,
  "votes_up": 658,
  "votes_down": 134,
  "comment_type": "ForumTopic",
  "gidfeature": "1636418037459185108",
  "gidfeature2": "4633735454895638461",
  "clan_steamid_original": "103582791433224455"
}