{
  "appid": "570",
  "classid": "4614293505",
  "instanceid": "0",
  "icon_url": "i0CoZ81Ui0m-9KwlBY1L_18myuGuq1wfhWSaZgMttydbPaERSR0Wqmu7LAocGJazz1j_VPnAwvWoIX6a2lB65oLn_mbwSBPlm4Tf-DpL6vanfK1iLr6XXWbHk-0usbM_SSvjxEV_sG7Xm4r6dCqVaQUhD8N1EecN40TukdW1Kaq8sLBJBVNK",
  "icon_url_large": "i0CoZ81Ui0m-9KwlBY1L_18myuGuq1wfhWSaZgMttydbPaERSR0Wqmu7LAocGJazz1j_VPnAwvWoIX6a2lB65oLn_mbwSBPlm4Tf-DpL6vanfK1iLs-fD3WXxKBy5bJrTXrhwB4ltz7QmI74dy6Va1dxD5MlEOFb4xa5w9DvP7-2tg3flcsbmvUNSly2",
  "icon_drag_url": "",
  "name": "Frozen Falchionaire",
  "market_hash_name": "Frozen Falchionaire",
  "market_name": "Frozen Falchionaire",
  "name_color": "D2D2D2",
  "background_color": "",
  "type": "Rare Bundle",
  "tradable": "1",
  "marketable": "1",
  "commodity": "0",
  "market_tradable_restriction": "7",
  "market_marketable_restriction": "7",
  "fraudwarnings": "",
  "descriptions": {
    "0": {
      "type": "html",
      "value": "Used By: Pangolier",
      "name": "attribute",
      "app_data": ""
    }
  },
  "owner_descriptions": "",
  "tags": {
    "0": {
      "internal_name": "unique",
      "name": "Standard",
      "category": "Quality",
      "color": "D2D2D2",
      "category_name": "Quality"
    },
    "1": {
      "internal_name": "Rarity_Rare",
      "name": "Rare",
      "category": "Rarity",
      "color": "4b69ff",
      "category_name": "Rarity"
    },
    "2": {
      "internal_name": "bundle",
      "name": "Bundle",
      "category": "Type",
      "category_name": "Type"
    },
    "3": {
      "internal_name": "none",
      "name": "N/A",
      "category": "Slot",
      "category_name": "Slot"
    },
    "4": {
      "internal_name": "npc_dota_hero_pangolier",
      "name": "Pangolier",
      "category": "Hero",
      "category_name": "Hero"
    }
  }
}