{
  "result": {
    "data": {
      "abilities": [
        {
          "id": 5073,
          "name": "puck_dream_coil",
          "name_loc": "Dream Coil",
          "desc_loc": "Creates a coil of volatile magic that latches onto enemy Heroes, damaging and leashing them.  If the enemy hero stretches the coil by moving too far away, it snaps, stunning and dealing additional damage.",
          "lore_loc": "The Faerie Dragon sows confusion by forcing its enemies to vividly dream about their own mortality.",
          "notes_loc": [],
          "shard_loc": "",
          "scepter_loc": "All enemies affected by Dream Coil are attacked at a rate equal to %attack_rate_pct%%% of Puck's attack rate. The attacks continue while the target is stunned if they break the Dream Coil.",
          "facets_loc": [],
          "type": 1,
          "behavior": "48",
          "target_team": 0,
          "target_type": 1,
          "flags": 0,
          "damage": 2,
          "immunity": 4,
          "dispellable": 3,
          "max_level": 3,
          "cast_ranges": [
            750
          ],
          "cast_points": [
            0.1,
            0.1,
            0.1
          ],
          "channel_times": [
            0
          ],
          "cooldowns": [
            75
          ],
          "durations": [
            0
          ],
          "damages": [
            0,
            0,
            0,
            0
          ],
          "mana_costs": [
            100,
            150,
            200
          ],
          "gold_costs": [],
          "health_costs": [],
          "special_values": [
            {
              "name": "coil_duration",
              "values_float": [
                6
              ],
              "is_percentage": false,
              "heading_loc": "COIL DURATION:",
              "bonuses": [],
              "values_shard": [],
              "values_scepter": [],
              "facet_bonus": {
                "name": "",
                "values": [],
                "operation": 0
              },
              "required_facet": ""
            },
            {
              "name": "coil_break_radius",
              "values_float": [
                600
              ],
              "is_percentage": false,
              "heading_loc": "BREAK RADIUS:",
              "bonuses": [],
              "values_shard": [],
              "values_scepter": [],
              "facet_bonus": {
                "name": "",
                "values": [],
                "operation": 0
              },
              "required_facet": ""
            },
            {
              "name": "stun_duration",
              "values_float": [
                0.5
              ],
              "is_percentage": false,
              "heading_loc": "",
              "bonuses": [],
              "values_shard": [],
              "values_scepter": [],
              "facet_bonus": {
                "name": "",
                "values": [],
                "operation": 0
              },
              "required_facet": ""
            },
            {
              "name": "coil_initial_damage",
              "values_float": [
                175,
                250,
                325
              ],
              "is_percentage": false,
              "heading_loc": "INITIAL DAMAGE:",
              "bonuses": [
                {
                  "name": "special_bonus_unique_puck_coil_damage",
                  "value": 150,
                  "operation": 0
                }
              ],
              "values_shard": [],
              "values_scepter": [],
              "facet_bonus": {
                "name": "",
                "values": [],
                "operation": 0
              },
              "required_facet": ""
            },
            {
              "name": "coil_stun_duration",
              "values_float": [
                1.5,
                2,
                2.5
              ],
              "is_percentage": false,
              "heading_loc": "BREAK STUN DURATION:",
              "bonuses": [],
              "values_shard": [],
              "values_scepter": [],
              "facet_bonus": {
                "name": "",
                "values": [],
                "operation": 0
              },
              "required_facet": ""
            },
            {
              "name": "coil_break_damage",
              "values_float": [
                200,
                300,
                400
              ],
              "is_percentage": false,
              "heading_loc": "BREAK DAMAGE:",
              "bonuses": [
                {
                  "name": "special_bonus_unique_puck_coil_damage",
                  "value": 175,
                  "operation": 0
                }
              ],
              "values_shard": [],
              "values_scepter": [],
              "facet_bonus": {
                "name": "",
                "values": [],
                "operation": 0
              },
              "required_facet": ""
            },
            {
              "name": "coil_radius",
              "values_float": [
                375
              ],
              "is_percentage": false,
              "heading_loc": "",
              "bonuses": [],
              "values_shard": [],
              "values_scepter": [],
              "facet_bonus": {
                "name": "",
                "values": [],
                "operation": 0
              },
              "required_facet": ""
            },
            {
              "name": "coil_rapid_fire_rate",
              "values_float": [
                0
              ],
              "is_percentage": false,
              "heading_loc": "",
              "bonuses": [],
              "values_shard": [],
              "values_scepter": [
                0.6
              ],
              "facet_bonus": {
                "name": "",
                "values": [],
                "operation": 0
              },
              "required_facet": ""
            },
            {
              "name": "coil_rapid_fire_z_offset",
              "values_float": [
                0
              ],
              "is_percentage": false,
              "heading_loc": "",
              "bonuses": [],
              "values_shard": [],
              "values_scepter": [
                150
              ],
              "facet_bonus": {
                "name": "",
                "values": [],
                "operation": 0
              },
              "required_facet": ""
            },
            {
              "name": "attack_rate_pct",
              "values_float": [
                0
              ],
              "is_percentage": false,
              "heading_loc": "",
              "bonuses": [],
              "values_shard": [],
              "values_scepter": [
                90
              ],
              "facet_bonus": {
                "name": "",
                "values": [],
                "operation": 0
              },
              "required_facet": ""
            },
            {
              "name": "AbilityCastRange",
              "values_float": [
                750
              ],
              "is_percentage": false,
              "heading_loc": "",
              "bonuses": [],
              "values_shard": [],
              "values_scepter": [],
              "facet_bonus": {
                "name": "",
                "values": [],
                "operation": 0
              },
              "required_facet": ""
            },
            {
              "name": "AbilityChannelTime",
              "values_float": [
                0
              ],
              "is_percentage": false,
              "heading_loc": "",
              "bonuses": [],
              "values_shard": [],
              "values_scepter": [],
              "facet_bonus": {
                "name": "",
                "values": [],
                "operation": 0
              },
              "required_facet": ""
            },
            {
              "name": "AbilityDuration",
              "values_float": [
                0
              ],
              "is_percentage": false,
              "heading_loc": "",
              "bonuses": [],
              "values_shard": [],
              "values_scepter": [],
              "facet_bonus": {
                "name": "",
                "values": [],
                "operation": 0
              },
              "required_facet": ""
            },
            {
              "name": "AbilityCastPoint",
              "values_float": [
                0.1
              ],
              "is_percentage": false,
              "heading_loc": "",
              "bonuses": [],
              "values_shard": [],
              "values_scepter": [],
              "facet_bonus": {
                "name": "",
                "values": [],
                "operation": 0
              },
              "required_facet": ""
            },
            {
              "name": "AbilityCharges",
              "values_float": [
                0
              ],
              "is_percentage": false,
              "heading_loc": "",
              "bonuses": [],
              "values_shard": [],
              "values_scepter": [],
              "facet_bonus": {
                "name": "",
                "values": [],
                "operation": 0
              },
              "required_facet": ""
            },
            {
              "name": "AbilityChargeRestoreTime",
              "values_float": [
                0
              ],
              "is_percentage": false,
              "heading_loc": "",
              "bonuses": [],
              "values_shard": [],
              "values_scepter": [],
              "facet_bonus": {
                "name": "",
                "values": [],
                "operation": 0
              },
              "required_facet": ""
            },
            {
              "name": "AbilityManaCost",
              "values_float": [
                100,
                150,
                200
              ],
              "is_percentage": false,
              "heading_loc": "",
              "bonuses": [],
              "values_shard": [],
              "values_scepter": [],
              "facet_bonus": {
                "name": "",
                "values": [],
                "operation": 0
              },
              "required_facet": ""
            },
            {
              "name": "AbilityCooldown",
              "values_float": [
                75
              ],
              "is_percentage": false,
              "heading_loc": "",
              "bonuses": [],
              "values_shard": [],
              "values_scepter": [],
              "facet_bonus": {
                "name": "",
                "values": [],
                "operation": 0
              },
              "required_facet": ""
            }
          ],
          "is_item": false,
          "ability_has_scepter": true,
          "ability_has_shard": false,
          "ability_is_granted_by_scepter": false,
          "ability_is_granted_by_shard": false,
          "ability_is_innate": false,
          "item_cost": 0,
          "item_initial_charges": 0,
          "item_neutral_tier": 4294967295,
          "item_stock_max": 0,
          "item_stock_time": 0,
          "item_quality": 0
        }
      ]
    },
    "status": 1
  }
}