{
  "result": {
    "data": {
      "heroes": [
        {
          "id": 83,
          "name": "npc_dota_hero_treant",
          "order_id": 76,
          "name_loc": "Treant Protector",
          "bio_loc": "Far to the west, in the mountains beyond the Vale of Augury, lie the remains of an ancient power, a fount of eldritch energy nestled deep in the high woods. It is said that the things that grow here, grow strangely. To the forces of nature this is a sacred place, made to stay hidden and unknown. Many are the traps and dangers of this land.  There are all-consuming grasses, crossbred fauna and poisonous flowers, but none are so fierce as the mighty Treant Protectors.\r\n\t\t\t\t<br><br>These ageless, titanic beings, charged with keeping the peace in this dangerous land, ensure that none within encroach without reason, and none without poach their secrets. For time untold they tended to their holy ground, uninterrupted, only dimly aware of the changing world beyond. Yet inevitably the wider world grew aware of this untamed land, and with each passing winter the outsiders grew bolder. Soon they arrived with tools to cut and with flames to burn, and often the Treants would ponder: who are these fragile, industrious creatures? What now had become of the wild, green world? There came and went an age of questions and of doubts, a thousand summers of long traditions set to scrutiny, while more and more the outsiders died and fed their earth.\r\n\t\t\t\t<br><br>When all that bloomed had finally finished their say, curiosity had overcome caution. It was decided: a lone Protector would be sent into the wider world, and instructed to wander until the glaciers arose once more, to observe the changing land and its creatures, and to discover what unknown dangers could threaten their sacred ground.",
          "hype_loc": "Treant Protector is ever the benevolent ally, sprouting <b>regenerating armor</b> for his cohorts and their fortifications alike. Emerging unseen from among the trees, he <b>binds foes</b> with overgrowth as he <b>leeches health</b> from enemies and into nearby allies.",
          "npe_desc_loc": "Calls upon the forest to root his foes",
          "facets": [
            {
              "color": 2,
              "title_loc": "Uprooted",
              "description_loc": "This facet doesn't do anything. Treant Protector is still finding his roots...",
              "name": "treant_treant",
              "icon": "tree",
              "gradient_id": 2,
              "index": 2
            }
          ],
          "str_base": 25,
          "str_gain": 3.4,
          "agi_base": 15,
          "agi_gain": 1.8,
          "int_base": 20,
          "int_gain": 1.8,
          "primary_attr": 0,
          "complexity": 2,
          "attack_capability": 1,
          "role_levels": [
            0,
            3,
            0,
            1,
            0,
            1,
            1,
            0,
            2
          ],
          "damage_min": 85,
          "damage_max": 93,
          "attack_rate": 1.9,
          "attack_range": 150,
          "projectile_speed": 900,
          "armor": 3.5,
          "magic_resistance": 25,
          "movement_speed": 280,
          "turn_rate": 0.6,
          "sight_range_day": 1800,
          "sight_range_night": 800,
          "max_health": 670,
          "health_regen": 2.75,
          "max_mana": 315,
          "mana_regen": 1.25,
          "abilities": [
            {
              "id": 338,
              "name": "treant_natures_grasp",
              "name_loc": "Nature's Grasp",
              "desc_loc": "Creates vines towards the target location. Vines slow down and deal damage to enemies that walk through. Does %creep_penalty%%% less damage to creeps.",
              "lore_loc": "The tendrils of Rooftrellen's influence stretch to all corners of the forest.",
              "notes_loc": [],
              "shard_loc": "",
              "scepter_loc": "",
              "facets_loc": [
                "",
                "",
                ""
              ],
              "type": 0,
              "behavior": "16",
              "target_team": 0,
              "target_type": 64,
              "flags": 0,
              "damage": 2,
              "immunity": 4,
              "dispellable": 0,
              "max_level": 4,
              "cast_ranges": [
                1500
              ],
              "cast_points": [
                0.2
              ],
              "channel_times": [
                0
              ],
              "cooldowns": [
                20,
                19,
                18,
                17
              ],
              "durations": [
                0
              ],
              "damages": [
                0,
                0,
                0,
                0
              ],
              "mana_costs": [
                90
              ],
              "gold_costs": [],
              "health_costs": [],
              "special_values": [
                {
                  "name": "damage_per_second",
                  "values_float": [
                    35,
                    50,
                    65,
                    80
                  ],
                  "is_percentage": false,
                  "heading_loc": "DAMAGE PER SECOND:",
                  "bonuses": [
                    {
                      "name": "special_bonus_unique_treant_9",
                      "value": 25,
                      "operation": 0
                    }
                  ],
                  "values_shard": [],
                  "values_scepter": [],
                  "facet_bonus": {
                    "name": "",
                    "values": [],
                    "operation": 0
                  },
                  "required_facet": ""
                },
                {
                  "name": "creep_penalty",
                  "values_float": [
                    35
                  ],
                  "is_percentage": false,
                  "heading_loc": "",
                  "bonuses": [],
                  "values_shard": [],
                  "values_scepter": [],
                  "facet_bonus": {
                    "name": "",
                    "values": [],
                    "operation": 0
                  },
                  "required_facet": ""
                },
                {
                  "name": "movement_slow",
                  "values_float": [
                    25,
                    30,
                    35,
                    40
                  ],
                  "is_percentage": true,
                  "heading_loc": "MOVEMENT SLOW:",
                  "bonuses": [],
                  "values_shard": [],
                  "values_scepter": [],
                  "facet_bonus": {
                    "name": "",
                    "values": [],
                    "operation": 0
                  },
                  "required_facet": ""
                },
                {
                  "name": "vines_duration",
                  "values_float": [
                    9,
                    10,
                    11,
                    12
                  ],
                  "is_percentage": false,
                  "heading_loc": "VINE DURATION:",
                  "bonuses": [],
                  "values_shard": [],
                  "values_scepter": [],
                  "facet_bonus": {
                    "name": "",
                    "values": [],
                    "operation": 0
                  },
                  "required_facet": ""
                },
                {
                  "name": "creation_interval",
                  "values_float": [
                    0.1
                  ],
                  "is_percentage": false,
                  "heading_loc": "",
                  "bonuses": [],
                  "values_shard": [],
                  "values_scepter": [],
                  "facet_bonus": {
                    "name": "",
                    "values": [],
                    "operation": 0
                  },
                  "required_facet": ""
                },
                {
                  "name": "initial_latch_delay",
                  "values_float": [
                    0.3
                  ],
                  "is_percentage": false,
                  "heading_loc": "",
                  "bonuses": [],
                  "values_shard": [],
                  "values_scepter": [],
                  "facet_bonus": {
                    "name": "",
                    "values": [],
                    "operation": 0
                  },
                  "required_facet": ""
                },
                {
                  "name": "vine_spawn_interval",
                  "values_float": [
                    175
                  ],
                  "is_percentage": false,
                  "heading_loc": "",
                  "bonuses": [],
                  "values_shard": [],
                  "values_scepter": [],
                  "facet_bonus": {
                    "name": "",
                    "values": [],
                    "operation": 0
                  },
                  "required_facet": ""
                },
                {
                  "name": "latch_range",
                  "values_float": [
                    135
                  ],
                  "is_percentage": false,
                  "heading_loc": "",
                  "bonuses": [],
                  "values_shard": [],
                  "values_scepter": [],
                  "facet_bonus": {
                    "name": "",
                    "values": [],
                    "operation": 0
                  },
                  "required_facet": ""
                },
                {
                  "name": "latch_vision",
                  "values_float": [
                    150
                  ],
                  "is_percentage": false,
                  "heading_loc": "",
                  "bonuses": [],
                  "values_shard": [],
                  "values_scepter": [],
                  "facet_bonus": {
                    "name": "",
                    "values": [],
                    "operation": 0
                  },
                  "required_facet": ""
                },
                {
                  "name": "AbilityCastRange",
                  "values_float": [
                    1500
                  ],
                  "is_percentage": false,
                  "heading_loc": "",
                  "bonuses": [],
                  "values_shard": [],
                  "values_scepter": [],
                  "facet_bonus": {
                    "name": "",
                    "values": [],
                    "operation": 0
                  },
                  "required_facet": ""
                },
                {
                  "name": "AbilityCastPoint",
                  "values_float": [
                    0.2
                  ],
                  "is_percentage": false,
                  "heading_loc": "",
                  "bonuses": [],
                  "values_shard": [],
                  "values_scepter": [],
                  "facet_bonus": {
                    "name": "",
                    "values": [],
                    "operation": 0
                  },
                  "required_facet": ""
                },
                {
                  "name": "AbilityManaCost",
                  "values_float": [
                    90
                  ],
                  "is_percentage": false,
                  "heading_loc": "",
                  "bonuses": [],
                  "values_shard": [],
                  "values_scepter": [],
                  "facet_bonus": {
                    "name": "",
                    "values": [],
                    "operation": 0
                  },
                  "required_facet": ""
                },
                {
                  "name": "AbilityCooldown",
                  "values_float": [
                    20,
                    19,
                    18,
                    17
                  ],
                  "is_percentage": false,
                  "heading_loc": "",
                  "bonuses": [],
                  "values_shard": [],
                  "values_scepter": [],
                  "facet_bonus": {
                    "name": "",
                    "values": [],
                    "operation": 0
                  },
                  "required_facet": ""
                }
              ],
              "is_item": false,
              "ability_has_scepter": false,
              "ability_has_shard": false,
              "ability_is_granted_by_scepter": false,
              "ability_is_granted_by_shard": false,
              "ability_is_innate": false,
              "item_cost": 0,
              "item_initial_charges": 0,
              "item_neutral_tier": 4294967295,
              "item_stock_max": 0,
              "item_stock_time": 0,
              "item_quality": 0
            },
            {
              "id": 5435,
              "name": "treant_leech_seed",
              "name_loc": "Leech Seed",
              "desc_loc": "Treant's attack plants a life-sapping seed in an enemy unit, dealing additional magic damage. The unit is then bound for a short duration and emits %healing_pulse_count% healing pulses to up to %max_heal_units% nearby allies of Treant Protector based on a flat amount and the damage dealt by the attack.",
              "lore_loc": "Rooftrellen nurtures the beings under his stewardship, sustained by the lifeforce of trespassers into his sacred ground.",
              "notes_loc": [],
              "shard_loc": "",
              "scepter_loc": "",
              "facets_loc": [
                "",
                "Leech Seed can be ground targeted, planting a tree that heals allies and damages all enemies in the effect radius for the duration of the ability. Damage to creeps is reduced by %creep_damage_reduction_pct%%%. If the tree is cut down, it immediately re-grows again.",
                ""
              ],
              "type": 0,
              "behavior": "135176",
              "target_team": 2,
              "target_type": 19,
              "flags": 0,
              "damage": 2,
              "immunity": 4,
              "dispellable": 2,
              "max_level": 4,
              "cast_ranges": [
                150
              ],
              "cast_points": [
                0
              ],
              "channel_times": [
                0
              ],
              "cooldowns": [
                15,
                12,
                9,
                6
              ],
              "durations": [
                0
              ],
              "damages": [
                0,
                0,
                0,
                0
              ],
              "mana_costs": [
                0
              ],
              "gold_costs": [],
              "health_costs": [],
              "special_values": [
                {
                  "name": "duration",
                  "values_float": [
                    0.9,
                    1.1,
                    1.3,
                    1.5
                  ],
                  "is_percentage": false,
                  "heading_loc": "DURATION:",
                  "bonuses": [],
                  "values_shard": [],
                  "values_scepter": [],
                  "facet_bonus": {
                    "name": "",
                    "values": [],
                    "operation": 0
                  },
                  "required_facet": ""
                },
                {
                  "name": "flat_heal",
                  "values_float": [
                    15,
                    25,
                    35,
                    45
                  ],
                  "is_percentage": false,
                  "heading_loc": "FLAT HEALING:",
                  "bonuses": [],
                  "values_shard": [],
                  "values_scepter": [],
                  "facet_bonus": {
                    "name": "",
                    "values": [],
                    "operation": 0
                  },
                  "required_facet": ""
                },
                {
                  "name": "leech_heal",
                  "values_float": [
                    20
                  ],
                  "is_percentage": true,
                  "heading_loc": "DAMAGE TO HEALING:",
                  "bonuses": [
                    {
                      "name": "special_bonus_unique_treant_3",
                      "value": 10,
                      "operation": 0
                    }
                  ],
                  "values_shard": [],
                  "values_scepter": [],
                  "facet_bonus": {
                    "name": "",
                    "values": [],
                    "operation": 0
                  },
                  "required_facet": ""
                },
                {
                  "name": "leech_damage",
                  "values_float": [
                    20,
                    40,
                    60,
                    80
                  ],
                  "is_percentage": false,
                  "heading_loc": "BONUS DAMAGE:",
                  "bonuses": [
                    {
                      "name": "special_bonus_unique_treant_2",
                      "value": 80,
                      "operation": 0
                    }
                  ],
                  "values_shard": [],
                  "values_scepter": [],
                  "facet_bonus": {
                    "name": "",
                    "values": [],
                    "operation": 0
                  },
                  "required_facet": ""
                },
                {
                  "name": "max_heal_units",
                  "values_float": [
                    5
                  ],
                  "is_percentage": false,
                  "heading_loc": "",
                  "bonuses": [],
                  "values_shard": [],
                  "values_scepter": [],
                  "facet_bonus": {
                    "name": "",
                    "values": [],
                    "operation": 0
                  },
                  "required_facet": ""
                },
                {
                  "name": "radius",
                  "values_float": [
                    650
                  ],
                  "is_percentage": false,
                  "heading_loc": "HEAL RADIUS:",
                  "bonuses": [],
                  "values_shard": [],
                  "values_scepter": [],
                  "facet_bonus": {
                    "name": "",
                    "values": [],
                    "operation": 0
                  },
                  "required_facet": ""
                },
                {
                  "name": "healing_pulse_count",
                  "values_float": [
                    2
                  ],
                  "is_percentage": false,
                  "heading_loc": "",
                  "bonuses": [],
                  "values_shard": [],
                  "values_scepter": [],
                  "facet_bonus": {
                    "name": "",
                    "values": [],
                    "operation": 0
                  },
                  "required_facet": ""
                },
                {
                  "name": "projectile_speed",
                  "values_float": [
                    450
                  ],
                  "is_percentage": false,
                  "heading_loc": "",
                  "bonuses": [],
                  "values_shard": [],
                  "values_scepter": [],
                  "facet_bonus": {
                    "name": "",
                    "values": [],
                    "operation": 0
                  },
                  "required_facet": ""
                },
                {
                  "name": "AbilityCastRange",
                  "values_float": [
                    150
                  ],
                  "is_percentage": false,
                  "heading_loc": "",
                  "bonuses": [],
                  "values_shard": [],
                  "values_scepter": [],
                  "facet_bonus": {
                    "name": "",
                    "values": [],
                    "operation": 0
                  },
                  "required_facet": ""
                },
                {
                  "name": "AbilityCooldown",
                  "values_float": [
                    15,
                    12,
                    9,
                    6
                  ],
                  "is_percentage": false,
                  "heading_loc": "",
                  "bonuses": [
                    {
                      "name": "special_bonus_unique_treant_14",
                      "value": 3,
                      "operation": 2
                    }
                  ],
                  "values_shard": [],
                  "values_scepter": [],
                  "facet_bonus": {
                    "name": "",
                    "values": [],
                    "operation": 0
                  },
                  "required_facet": ""
                }
              ],
              "is_item": false,
              "ability_has_scepter": false,
              "ability_has_shard": false,
              "ability_is_granted_by_scepter": false,
              "ability_is_granted_by_shard": false,
              "ability_is_innate": false,
              "item_cost": 0,
              "item_initial_charges": 0,
              "item_neutral_tier": 4294967295,
              "item_stock_max": 0,
              "item_stock_time": 0,
              "item_quality": 0
            },
            {
              "id": 5436,
              "name": "treant_living_armor",
              "name_loc": "Living Armor",
              "desc_loc": "Infuses the target hero or structure with a protective coating which heals the target and blocks damage from player-controlled sources. Each time this spell blocks damage, the block amount is decreased. If the damage block is decreased to 0, the buff is removed early.",
              "lore_loc": "The roots and tendrils of the Treant Protectors are far-reaching, stimulating the growth and rejuvenation of all of nature.",
              "notes_loc": [
                "Instances of damage less than %damage_block_threshold% are ignored."
              ],
              "shard_loc": "Increases the Damage Blocked by Living Armor. Treant now also passively benefits from Living Armor, with the damage block resetting after not taking damage for %passive_reset_cd% seconds.",
              "scepter_loc": "",
              "facets_loc": [
                "",
                "",
                ""
              ],
              "type": 0,
              "behavior": "24",
              "target_team": 1,
              "target_type": 23,
              "flags": 0,
              "damage": 0,
              "immunity": 1,
              "dispellable": 2,
              "max_level": 4,
              "cast_ranges": [
                0
              ],
              "cast_points": [
                0.3
              ],
              "channel_times": [
                0
              ],
              "cooldowns": [
                24,
                21,
                18,
                15
              ],
              "durations": [
                0
              ],
              "damages": [
                0,
                0,
                0,
                0
              ],
              "mana_costs": [
                40,
                45,
                50,
                55
              ],
              "gold_costs": [],
              "health_costs": [],
              "special_values": [
                {
                  "name": "heal_per_second",
                  "values_float": [
                    4,
                    7,
                    10,
                    13
                  ],
                  "is_percentage": false,
                  "heading_loc": "HEAL PER SECOND:",
                  "bonuses": [
                    {
                      "name": "special_bonus_unique_treant_8",
                      "value": 4,
                      "operation": 0
                    }
                  ],
                  "values_shard": [],
                  "values_scepter": [],
                  "facet_bonus": {
                    "name": "",
                    "values": [],
                    "operation": 0
                  },
                  "required_facet": ""
                },
                {
                  "name": "duration",
                  "values_float": [
                    12
                  ],
                  "is_percentage": false,
                  "heading_loc": "MAX DURATION:",
                  "bonuses": [],
                  "values_shard": [],
                  "values_scepter": [],
                  "facet_bonus": {
                    "name": "",
                    "values": [],
                    "operation": 0
                  },
                  "required_facet": ""
                },
                {
                  "name": "aoe_radius",
                  "values_float": [],
                  "is_percentage": false,
                  "heading_loc": "",
                  "bonuses": [
                    {
                      "name": "special_bonus_unique_treant_7",
                      "value": 450,
                      "operation": 0
                    }
                  ],
                  "values_shard": [],
                  "values_scepter": [],
                  "facet_bonus": {
                    "name": "",
                    "values": [],
                    "operation": 0
                  },
                  "required_facet": ""
                },
                {
                  "name": "damage_block_base",
                  "values_float": [
                    120
                  ],
                  "is_percentage": false,
                  "heading_loc": "DAMAGE BLOCKED:",
                  "bonuses": [
                    {
                      "name": "special_bonus_unique_treant_13",
                      "value": 20,
                      "operation": 0
                    }
                  ],
                  "values_shard": [],
                  "values_scepter": [],
                  "facet_bonus": {
                    "name": "",
                    "values": [],
                    "operation": 0
                  },
                  "required_facet": ""
                },
                {
                  "name": "passive_reset_cd",
                  "values_float": [
                    0
                  ],
                  "is_percentage": false,
                  "heading_loc": "",
                  "bonuses": [],
                  "values_shard": [
                    0
                  ],
                  "values_scepter": [],
                  "facet_bonus": {
                    "name": "",
                    "values": [],
                    "operation": 0
                  },
                  "required_facet": ""
                },
                {
                  "name": "damage_block_loss",
                  "values_float": [
                    35,
                    30,
                    25,
                    20
                  ],
                  "is_percentage": false,
                  "heading_loc": "DAMAGE BLOCK DECREASE:",
                  "bonuses": [],
                  "values_shard": [],
                  "values_scepter": [],
                  "facet_bonus": {
                    "name": "",
                    "values": [],
                    "operation": 0
                  },
                  "required_facet": ""
                },
                {
                  "name": "damage_block_threshold",
                  "values_float": [
                    20
                  ],
                  "is_percentage": false,
                  "heading_loc": "",
                  "bonuses": [],
                  "values_shard": [],
                  "values_scepter": [],
                  "facet_bonus": {
                    "name": "",
                    "values": [],
                    "operation": 0
                  },
                  "required_facet": ""
                },
                {
                  "name": "AbilityCastPoint",
                  "values_float": [
                    0.3
                  ],
                  "is_percentage": false,
                  "heading_loc": "",
                  "bonuses": [],
                  "values_shard": [],
                  "values_scepter": [],
                  "facet_bonus": {
                    "name": "",
                    "values": [],
                    "operation": 0
                  },
                  "required_facet": ""
                },
                {
                  "name": "AbilityManaCost",
                  "values_float": [
                    40,
                    45,
                    50,
                    55
                  ],
                  "is_percentage": false,
                  "heading_loc": "",
                  "bonuses": [],
                  "values_shard": [],
                  "values_scepter": [],
                  "facet_bonus": {
                    "name": "",
                    "values": [],
                    "operation": 0
                  },
                  "required_facet": ""
                },
                {
                  "name": "AbilityCooldown",
                  "values_float": [
                    24,
                    21,
                    18,
                    15
                  ],
                  "is_percentage": false,
                  "heading_loc": "",
                  "bonuses": [],
                  "values_shard": [],
                  "values_scepter": [],
                  "facet_bonus": {
                    "name": "",
                    "values": [],
                    "operation": 0
                  },
                  "required_facet": ""
                }
              ],
              "is_item": false,
              "ability_has_scepter": false,
              "ability_has_shard": false,
              "ability_is_granted_by_scepter": false,
              "ability_is_granted_by_shard": false,
              "ability_is_innate": false,
              "item_cost": 0,
              "item_initial_charges": 0,
              "item_neutral_tier": 4294967295,
              "item_stock_max": 0,
              "item_stock_time": 0,
              "item_quality": 0
            },
            {
              "id": 5649,
              "name": "treant_eyes_in_the_forest",
              "name_loc": "Eyes In The Forest",
              "desc_loc": "Treant Protector enchants a tree, which grants him unobstructed vision in that location. The eyes last for %duration% seconds and are invisible, but are destroyed if their host tree is destroyed or if they are attacked directly.",
              "lore_loc": "One can never be too certain who, or what, might need protecting.",
              "notes_loc": [
                "Being entangled by Overgrowth through enchanted trees from Eyes in the Forest does damage.",
                "If the enemy has True Sight, they will be able to see which trees are enchanted."
              ],
              "shard_loc": "",
              "scepter_loc": "",
              "facets_loc": [
                "",
                "",
                ""
              ],
              "type": 0,
              "behavior": "8589934601",
              "target_team": 0,
              "target_type": 64,
              "flags": 0,
              "damage": 0,
              "immunity": 0,
              "dispellable": 0,
              "max_level": 1,
              "cast_ranges": [
                350
              ],
              "cast_points": [
                0.2
              ],
              "channel_times": [
                0
              ],
              "cooldowns": [
                0
              ],
              "durations": [
                0
              ],
              "damages": [
                0,
                0,
                0,
                0
              ],
              "mana_costs": [
                30
              ],
              "gold_costs": [],
              "health_costs": [],
              "special_values": [
                {
                  "name": "vision_aoe",
                  "values_float": [
                    800
                  ],
                  "is_percentage": false,
                  "heading_loc": "",
                  "bonuses": [],
                  "values_shard": [],
                  "values_scepter": [],
                  "facet_bonus": {
                    "name": "",
                    "values": [],
                    "operation": 0
                  },
                  "required_facet": ""
                },
                {
                  "name": "hits_to_kill",
                  "values_float": [
                    2
                  ],
                  "is_percentage": false,
                  "heading_loc": "",
                  "bonuses": [],
                  "values_shard": [],
                  "values_scepter": [],
                  "facet_bonus": {
                    "name": "",
                    "values": [],
                    "operation": 0
                  },
                  "required_facet": ""
                },
                {
                  "name": "duration",
                  "values_float": [
                    300
                  ],
                  "is_percentage": false,
                  "heading_loc": "",
                  "bonuses": [],
                  "values_shard": [],
                  "values_scepter": [],
                  "facet_bonus": {
                    "name": "",
                    "values": [],
                    "operation": 0
                  },
                  "required_facet": ""
                },
                {
                  "name": "AbilityCastRange",
                  "values_float": [
                    350
                  ],
                  "is_percentage": false,
                  "heading_loc": "",
                  "bonuses": [],
                  "values_shard": [],
                  "values_scepter": [],
                  "facet_bonus": {
                    "name": "",
                    "values": [],
                    "operation": 0
                  },
                  "required_facet": ""
                },
                {
                  "name": "AbilityCastPoint",
                  "values_float": [
                    0.2
                  ],
                  "is_percentage": false,
                  "heading_loc": "",
                  "bonuses": [],
                  "values_shard": [],
                  "values_scepter": [],
                  "facet_bonus": {
                    "name": "",
                    "values": [],
                    "operation": 0
                  },
                  "required_facet": ""
                },
                {
                  "name": "AbilityCharges",
                  "values_float": [
                    3
                  ],
                  "is_percentage": false,
                  "heading_loc": "",
                  "bonuses": [],
                  "values_shard": [],
                  "values_scepter": [],
                  "facet_bonus": {
                    "name": "",
                    "values": [],
                    "operation": 0
                  },
                  "required_facet": ""
                },
                {
                  "name": "AbilityChargeRestoreTime",
                  "values_float": [
                    55
                  ],
                  "is_percentage": false,
                  "heading_loc": "",
                  "bonuses": [],
                  "values_shard": [],
                  "values_scepter": [],
                  "facet_bonus": {
                    "name": "",
                    "values": [],
                    "operation": 0
                  },
                  "required_facet": ""
                },
                {
                  "name": "AbilityManaCost",
                  "values_float": [
                    30
                  ],
                  "is_percentage": false,
                  "heading_loc": "",
                  "bonuses": [],
                  "values_shard": [],
                  "values_scepter": [],
                  "facet_bonus": {
                    "name": "",
                    "values": [],
                    "operation": 0
                  },
                  "required_facet": ""
                }
              ],
              "is_item": false,
              "ability_has_scepter": false,
              "ability_has_shard": true,
              "ability_is_granted_by_scepter": false,
              "ability_is_granted_by_shard": true,
              "ability_is_innate": false,
              "item_cost": 0,
              "item_initial_charges": 0,
              "item_neutral_tier": 4294967295,
              "item_stock_max": 0,
              "item_stock_time": 0,
              "item_quality": 0
            },
            {
              "id": 5434,
              "name": "treant_natures_guise",
              "name_loc": "Nature's Guise",
              "desc_loc": "Grants bonus movement speed when near trees. Treant Protector additionally has Tree Walking if he has not taken damage for %cooldown_time% seconds. While Tree Walking, Nature's Guise can be activated to grant Treant invisibility until he attacks or is no longer near a tree.",
              "lore_loc": "The Protectors don't often come into vision; their natural state being nestled within their leafy brethren.",
              "notes_loc": [
                "While affected by Nature's Guise, Treant can move unobstructed through other trees.",
                "Vines from Nature's Grasp are considered trees for this ability.",
                "While Tree Walking, taking damage does not disable the active ability or Tree Walking."
              ],
              "shard_loc": "",
              "scepter_loc": "",
              "facets_loc": [
                "",
                "",
                ""
              ],
              "type": 0,
              "behavior": "8589934658",
              "target_team": 0,
              "target_type": 0,
              "flags": 0,
              "damage": 0,
              "immunity": 0,
              "dispellable": 0,
              "max_level": 1,
              "cast_ranges": [
                0
              ],
              "cast_points": [
                0
              ],
              "channel_times": [
                0
              ],
              "cooldowns": [
                35
              ],
              "durations": [
                0
              ],
              "damages": [
                0,
                0,
                0,
                0
              ],
              "mana_costs": [
                0
              ],
              "gold_costs": [],
              "health_costs": [],
              "special_values": [
                {
                  "name": "radius",
                  "values_float": [
                    200
                  ],
                  "is_percentage": false,
                  "heading_loc": "",
                  "bonuses": [],
                  "values_shard": [],
                  "values_scepter": [],
                  "facet_bonus": {
                    "name": "",
                    "values": [],
                    "operation": 0
                  },
                  "required_facet": ""
                },
                {
                  "name": "grace_time",
                  "values_float": [
                    2
                  ],
                  "is_percentage": false,
                  "heading_loc": "",
                  "bonuses": [],
                  "values_shard": [],
                  "values_scepter": [],
                  "facet_bonus": {
                    "name": "",
                    "values": [],
                    "operation": 0
                  },
                  "required_facet": ""
                },
                {
                  "name": "cooldown_time",
                  "values_float": [
                    2.75
                  ],
                  "is_percentage": false,
                  "heading_loc": "",
                  "bonuses": [],
                  "values_shard": [],
                  "values_scepter": [],
                  "facet_bonus": {
                    "name": "",
                    "values": [],
                    "operation": 0
                  },
                  "required_facet": ""
                },
                {
                  "name": "movement_bonus",
                  "values_float": [
                    10
                  ],
                  "is_percentage": true,
                  "heading_loc": "MOVEMENT SPEED BONUS:",
                  "bonuses": [
                    {
                      "name": "special_bonus_unique_treant_12",
                      "value": 2.5,
                      "operation": 0
                    }
                  ],
                  "values_shard": [],
                  "values_scepter": [],
                  "facet_bonus": {
                    "name": "",
                    "values": [],
                    "operation": 0
                  },
                  "required_facet": ""
                },
                {
                  "name": "AbilityCooldown",
                  "values_float": [
                    35
                  ],
                  "is_percentage": false,
                  "heading_loc": "COOLDOWN:",
                  "bonuses": [],
                  "values_shard": [],
                  "values_scepter": [],
                  "facet_bonus": {
                    "name": "",
                    "values": [],
                    "operation": 0
                  },
                  "required_facet": ""
                }
              ],
              "is_item": false,
              "ability_has_scepter": false,
              "ability_has_shard": false,
              "ability_is_granted_by_scepter": false,
              "ability_is_granted_by_shard": false,
              "ability_is_innate": true,
              "item_cost": 0,
              "item_initial_charges": 0,
              "item_neutral_tier": 4294967295,
              "item_stock_max": 0,
              "item_stock_time": 0,
              "item_quality": 0
            },
            {
              "id": 5437,
              "name": "treant_overgrowth",
              "name_loc": "Overgrowth",
              "desc_loc": "Summons an overgrowth of vines and branches around Treant that deal damage to afflicted enemies and prevent them from moving, blinking, going invisible, or attacking.",
              "lore_loc": "Rooftrellen calls the ancestral spirit of nature, releasing its power through all of his kin.",
              "notes_loc": [
                "Works on Debuff Immune units, but if units gain debuff immunity after the effect starts, they'll break free."
              ],
              "shard_loc": "",
              "scepter_loc": "Decreases Cooldown to %AbilityCooldown% seconds. When casting Overgrowth, Treant Protector draws power from the soil, gaining an undispellable buff that greatly increasing his size for %bloom_duration% seconds. While enlarged, he gains phased movement with a fixed speed of %movement_speed%, %strength_bonus%%% bonus Strength, and a splashing attack that deals %splash_pct%%% of his attack damage in a %splash_radius% unit radius.",
              "facets_loc": [
                "",
                "",
                ""
              ],
              "type": 1,
              "behavior": "4",
              "target_team": 0,
              "target_type": 0,
              "flags": 0,
              "damage": 2,
              "immunity": 3,
              "dispellable": 2,
              "max_level": 3,
              "cast_ranges": [
                0
              ],
              "cast_points": [
                0.5,
                0.5,
                0.5,
                0.5
              ],
              "channel_times": [
                0
              ],
              "cooldowns": [
                110,
                100,
                90
              ],
              "durations": [
                0
              ],
              "damages": [
                0,
                0,
                0,
                0
              ],
              "mana_costs": [
                200,
                250,
                300
              ],
              "gold_costs": [],
              "health_costs": [],
              "special_values": [
                {
                  "name": "duration",
                  "values_float": [
                    3,
                    4,
                    5
                  ],
                  "is_percentage": false,
                  "heading_loc": "DURATION:",
                  "bonuses": [],
                  "values_shard": [],
                  "values_scepter": [],
                  "facet_bonus": {
                    "name": "",
                    "values": [],
                    "operation": 0
                  },
                  "required_facet": ""
                },
                {
                  "name": "radius",
                  "values_float": [
                    800
                  ],
                  "is_percentage": false,
                  "heading_loc": "RADIUS:",
                  "bonuses": [],
                  "values_shard": [],
                  "values_scepter": [],
                  "facet_bonus": {
                    "name": "",
                    "values": [],
                    "operation": 0
                  },
                  "required_facet": ""
                },
                {
                  "name": "damage",
                  "values_float": [
                    95
                  ],
                  "is_percentage": false,
                  "heading_loc": "DAMAGE PER SECOND:",
                  "bonuses": [],
                  "values_shard": [],
                  "values_scepter": [],
                  "facet_bonus": {
                    "name": "",
                    "values": [],
                    "operation": 0
                  },
                  "required_facet": ""
                },
                {
                  "name": "bloom_duration",
                  "values_float": [
                    0
                  ],
                  "is_percentage": false,
                  "heading_loc": "",
                  "bonuses": [],
                  "values_shard": [],
                  "values_scepter": [
                    16
                  ],
                  "facet_bonus": {
                    "name": "",
                    "values": [],
                    "operation": 0
                  },
                  "required_facet": ""
                },
                {
                  "name": "strength_bonus",
                  "values_float": [
                    0
                  ],
                  "is_percentage": false,
                  "heading_loc": "",
                  "bonuses": [],
                  "values_shard": [],
                  "values_scepter": [
                    100
                  ],
                  "facet_bonus": {
                    "name": "",
                    "values": [],
                    "operation": 0
                  },
                  "required_facet": ""
                },
                {
                  "name": "splash_pct",
                  "values_float": [
                    0
                  ],
                  "is_percentage": false,
                  "heading_loc": "",
                  "bonuses": [],
                  "values_shard": [],
                  "values_scepter": [
                    60
                  ],
                  "facet_bonus": {
                    "name": "",
                    "values": [],
                    "operation": 0
                  },
                  "required_facet": ""
                },
                {
                  "name": "splash_radius",
                  "values_float": [
                    0
                  ],
                  "is_percentage": false,
                  "heading_loc": "",
                  "bonuses": [],
                  "values_shard": [],
                  "values_scepter": [
                    300
                  ],
                  "facet_bonus": {
                    "name": "",
                    "values": [],
                    "operation": 0
                  },
                  "required_facet": ""
                },
                {
                  "name": "movement_speed",
                  "values_float": [
                    0
                  ],
                  "is_percentage": false,
                  "heading_loc": "",
                  "bonuses": [],
                  "values_shard": [],
                  "values_scepter": [
                    345
                  ],
                  "facet_bonus": {
                    "name": "",
                    "values": [],
                    "operation": 0
                  },
                  "required_facet": ""
                },
                {
                  "name": "AbilityCastPoint",
                  "values_float": [
                    0.5
                  ],
                  "is_percentage": false,
                  "heading_loc": "",
                  "bonuses": [],
                  "values_shard": [],
                  "values_scepter": [],
                  "facet_bonus": {
                    "name": "",
                    "values": [],
                    "operation": 0
                  },
                  "required_facet": ""
                },
                {
                  "name": "AbilityManaCost",
                  "values_float": [
                    200,
                    250,
                    300
                  ],
                  "is_percentage": false,
                  "heading_loc": "",
                  "bonuses": [],
                  "values_shard": [],
                  "values_scepter": [],
                  "facet_bonus": {
                    "name": "",
                    "values": [],
                    "operation": 0
                  },
                  "required_facet": ""
                },
                {
                  "name": "AbilityCooldown",
                  "values_float": [
                    110,
                    100,
                    90
                  ],
                  "is_percentage": false,
                  "heading_loc": "",
                  "bonuses": [],
                  "values_shard": [],
                  "values_scepter": [
                    25
                  ],
                  "facet_bonus": {
                    "name": "",
                    "values": [],
                    "operation": 0
                  },
                  "required_facet": ""
                }
              ],
              "is_item": false,
              "ability_has_scepter": true,
              "ability_has_shard": false,
              "ability_is_granted_by_scepter": false,
              "ability_is_granted_by_shard": false,
              "ability_is_innate": false,
              "item_cost": 0,
              "item_initial_charges": 0,
              "item_neutral_tier": 4294967295,
              "item_stock_max": 0,
              "item_stock_time": 0,
              "item_quality": 0
            }
          ],
          "talents": [
            {
              "id": 339,
              "name": "special_bonus_unique_treant_8",
              "name_loc": "+{s:bonus_heal_per_second} Living Armor Heal Per Second",
              "desc_loc": "",
              "lore_loc": "",
              "notes_loc": [],
              "shard_loc": "",
              "scepter_loc": "",
              "facets_loc": [
                "",
                "",
                ""
              ],
              "type": 2,
              "behavior": "2",
              "target_team": 0,
              "target_type": 0,
              "flags": 0,
              "damage": 0,
              "immunity": 0,
              "dispellable": 0,
              "max_level": 4,
              "cast_ranges": [
                0
              ],
              "cast_points": [
                0
              ],
              "channel_times": [
                0
              ],
              "cooldowns": [
                0
              ],
              "durations": [
                0
              ],
              "damages": [
                0,
                0,
                0,
                0
              ],
              "mana_costs": [
                0
              ],
              "gold_costs": [],
              "health_costs": [],
              "special_values": [],
              "is_item": false,
              "ability_has_scepter": false,
              "ability_has_shard": false,
              "ability_is_granted_by_scepter": false,
              "ability_is_granted_by_shard": false,
              "ability_is_innate": false,
              "item_cost": 0,
              "item_initial_charges": 0,
              "item_neutral_tier": 4294967295,
              "item_stock_max": 0,
              "item_stock_time": 0,
              "item_quality": 0
            },
            {
              "id": 548,
              "name": "special_bonus_attack_base_damage_50",
              "name_loc": "+{s:value} Base Damage",
              "desc_loc": "",
              "lore_loc": "",
              "notes_loc": [],
              "shard_loc": "",
              "scepter_loc": "",
              "facets_loc": [
                "",
                "",
                ""
              ],
              "type": 2,
              "behavior": "2",
              "target_team": 0,
              "target_type": 0,
              "flags": 0,
              "damage": 0,
              "immunity": 0,
              "dispellable": 0,
              "max_level": 4,
              "cast_ranges": [
                0
              ],
              "cast_points": [
                0
              ],
              "channel_times": [
                0
              ],
              "cooldowns": [
                0
              ],
              "durations": [
                0
              ],
              "damages": [
                0,
                0,
                0,
                0
              ],
              "mana_costs": [
                0
              ],
              "gold_costs": [],
              "health_costs": [],
              "special_values": [
                {
                  "name": "value",
                  "values_float": [
                    50
                  ],
                  "is_percentage": false,
                  "heading_loc": "",
                  "bonuses": [],
                  "values_shard": [],
                  "values_scepter": [],
                  "facet_bonus": {
                    "name": "",
                    "values": [],
                    "operation": 0
                  },
                  "required_facet": ""
                }
              ],
              "is_item": false,
              "ability_has_scepter": false,
              "ability_has_shard": false,
              "ability_is_granted_by_scepter": false,
              "ability_is_granted_by_shard": false,
              "ability_is_innate": false,
              "item_cost": 0,
              "item_initial_charges": 0,
              "item_neutral_tier": 4294967295,
              "item_stock_max": 0,
              "item_stock_time": 0,
              "item_quality": 0
            },
            {
              "id": 6955,
              "name": "special_bonus_unique_treant_3",
              "name_loc": "+{s:bonus_leech_heal}% Leech Seed Damage to Healing",
              "desc_loc": "",
              "lore_loc": "",
              "notes_loc": [],
              "shard_loc": "",
              "scepter_loc": "",
              "facets_loc": [
                "",
                "",
                ""
              ],
              "type": 2,
              "behavior": "2",
              "target_team": 0,
              "target_type": 0,
              "flags": 0,
              "damage": 0,
              "immunity": 0,
              "dispellable": 0,
              "max_level": 4,
              "cast_ranges": [
                0
              ],
              "cast_points": [
                0
              ],
              "channel_times": [
                0
              ],
              "cooldowns": [
                0
              ],
              "durations": [
                0
              ],
              "damages": [
                0,
                0,
                0,
                0
              ],
              "mana_costs": [
                0
              ],
              "gold_costs": [],
              "health_costs": [],
              "special_values": [],
              "is_item": false,
              "ability_has_scepter": false,
              "ability_has_shard": false,
              "ability_is_granted_by_scepter": false,
              "ability_is_granted_by_shard": false,
              "ability_is_innate": false,
              "item_cost": 0,
              "item_initial_charges": 0,
              "item_neutral_tier": 4294967295,
              "item_stock_max": 0,
              "item_stock_time": 0,
              "item_quality": 0
            },
            {
              "id": 340,
              "name": "special_bonus_unique_treant_9",
              "name_loc": "+{s:bonus_damage_per_second} Nature's Grasp Damage",
              "desc_loc": "",
              "lore_loc": "",
              "notes_loc": [],
              "shard_loc": "",
              "scepter_loc": "",
              "facets_loc": [
                "",
                "",
                ""
              ],
              "type": 2,
              "behavior": "2",
              "target_team": 0,
              "target_type": 0,
              "flags": 0,
              "damage": 0,
              "immunity": 0,
              "dispellable": 0,
              "max_level": 4,
              "cast_ranges": [
                0
              ],
              "cast_points": [
                0
              ],
              "channel_times": [
                0
              ],
              "cooldowns": [
                0
              ],
              "durations": [
                0
              ],
              "damages": [
                0,
                0,
                0,
                0
              ],
              "mana_costs": [
                0
              ],
              "gold_costs": [],
              "health_costs": [],
              "special_values": [],
              "is_item": false,
              "ability_has_scepter": false,
              "ability_has_shard": false,
              "ability_is_granted_by_scepter": false,
              "ability_is_granted_by_shard": false,
              "ability_is_innate": false,
              "item_cost": 0,
              "item_initial_charges": 0,
              "item_neutral_tier": 4294967295,
              "item_stock_max": 0,
              "item_stock_time": 0,
              "item_quality": 0
            },
            {
              "id": 756,
              "name": "special_bonus_unique_treant_13",
              "name_loc": "+{s:bonus_damage_block_base} Living Armor Damage Block",
              "desc_loc": "",
              "lore_loc": "",
              "notes_loc": [],
              "shard_loc": "",
              "scepter_loc": "",
              "facets_loc": [
                "",
                "",
                ""
              ],
              "type": 2,
              "behavior": "2",
              "target_team": 0,
              "target_type": 0,
              "flags": 0,
              "damage": 0,
              "immunity": 0,
              "dispellable": 0,
              "max_level": 4,
              "cast_ranges": [
                0
              ],
              "cast_points": [
                0
              ],
              "channel_times": [
                0
              ],
              "cooldowns": [
                0
              ],
              "durations": [
                0
              ],
              "damages": [
                0,
                0,
                0,
                0
              ],
              "mana_costs": [
                0
              ],
              "gold_costs": [],
              "health_costs": [],
              "special_values": [],
              "is_item": false,
              "ability_has_scepter": false,
              "ability_has_shard": false,
              "ability_is_granted_by_scepter": false,
              "ability_is_granted_by_shard": false,
              "ability_is_innate": false,
              "item_cost": 0,
              "item_initial_charges": 0,
              "item_neutral_tier": 4294967295,
              "item_stock_max": 0,
              "item_stock_time": 0,
              "item_quality": 0
            },
            {
              "id": 6531,
              "name": "special_bonus_unique_treant_2",
              "name_loc": "+{s:bonus_leech_damage} Leech Seed Bonus Damage",
              "desc_loc": "",
              "lore_loc": "",
              "notes_loc": [],
              "shard_loc": "",
              "scepter_loc": "",
              "facets_loc": [
                "",
                "",
                ""
              ],
              "type": 2,
              "behavior": "2",
              "target_team": 0,
              "target_type": 0,
              "flags": 0,
              "damage": 0,
              "immunity": 0,
              "dispellable": 0,
              "max_level": 4,
              "cast_ranges": [
                0
              ],
              "cast_points": [
                0
              ],
              "channel_times": [
                0
              ],
              "cooldowns": [
                0
              ],
              "durations": [
                0
              ],
              "damages": [
                0,
                0,
                0,
                0
              ],
              "mana_costs": [
                0
              ],
              "gold_costs": [],
              "health_costs": [],
              "special_values": [],
              "is_item": false,
              "ability_has_scepter": false,
              "ability_has_shard": false,
              "ability_is_granted_by_scepter": false,
              "ability_is_granted_by_shard": false,
              "ability_is_innate": false,
              "item_cost": 0,
              "item_initial_charges": 0,
              "item_neutral_tier": 4294967295,
              "item_stock_max": 0,
              "item_stock_time": 0,
              "item_quality": 0
            },
            {
              "id": 1131,
              "name": "special_bonus_unique_treant_14",
              "name_loc": "-{s:bonus_AbilityCooldown}s Leech Seed Cooldown",
              "desc_loc": "",
              "lore_loc": "",
              "notes_loc": [],
              "shard_loc": "",
              "scepter_loc": "",
              "facets_loc": [
                "",
                "",
                ""
              ],
              "type": 2,
              "behavior": "2",
              "target_team": 0,
              "target_type": 0,
              "flags": 0,
              "damage": 0,
              "immunity": 0,
              "dispellable": 0,
              "max_level": 4,
              "cast_ranges": [
                0
              ],
              "cast_points": [
                0
              ],
              "channel_times": [
                0
              ],
              "cooldowns": [
                0
              ],
              "durations": [
                0
              ],
              "damages": [
                0,
                0,
                0,
                0
              ],
              "mana_costs": [
                0
              ],
              "gold_costs": [],
              "health_costs": [],
              "special_values": [],
              "is_item": false,
              "ability_has_scepter": false,
              "ability_has_shard": false,
              "ability_is_granted_by_scepter": false,
              "ability_is_granted_by_shard": false,
              "ability_is_innate": false,
              "item_cost": 0,
              "item_initial_charges": 0,
              "item_neutral_tier": 4294967295,
              "item_stock_max": 0,
              "item_stock_time": 0,
              "item_quality": 0
            },
            {
              "id": 7115,
              "name": "special_bonus_unique_treant_7",
              "name_loc": "{s:bonus_aoe_radius} AoE Living Armor",
              "desc_loc": "",
              "lore_loc": "",
              "notes_loc": [],
              "shard_loc": "",
              "scepter_loc": "",
              "facets_loc": [
                "",
                "",
                ""
              ],
              "type": 2,
              "behavior": "2",
              "target_team": 0,
              "target_type": 0,
              "flags": 0,
              "damage": 0,
              "immunity": 0,
              "dispellable": 0,
              "max_level": 4,
              "cast_ranges": [
                0
              ],
              "cast_points": [
                0
              ],
              "channel_times": [
                0
              ],
              "cooldowns": [
                0
              ],
              "durations": [
                0
              ],
              "damages": [
                0,
                0,
                0,
                0
              ],
              "mana_costs": [
                0
              ],
              "gold_costs": [],
              "health_costs": [],
              "special_values": [],
              "is_item": false,
              "ability_has_scepter": false,
              "ability_has_shard": false,
              "ability_is_granted_by_scepter": false,
              "ability_is_granted_by_shard": false,
              "ability_is_innate": false,
              "item_cost": 0,
              "item_initial_charges": 0,
              "item_neutral_tier": 4294967295,
              "item_stock_max": 0,
              "item_stock_time": 0,
              "item_quality": 0
            }
          ],
          "facet_abilities": [
            {
              "abilities": []
            }
          ]
        }
      ]
    },
    "status": 1
  }
}