{
  "gid": "537750912402194535",
  "clan_steamid": "103582791433224455",
  "event_name": "Aggiornamento di gioco 7.40c",
  "event_type": 12,
  "appid": 570,
  "server_address": null,
  "server_password": null,
  "rtime32_start_time": 1769041380,
  "rtime32_end_time": 1769045401,
  "comment_count": 0,
  "creator_steamid": "0",
  "last_update_steamid": "0",
  "event_notes": "see announcement body",
  "jsondata": {
    "localized_title_image": [],
    "localized_capsule_image": [
      "98be0d0a60eca8edbad91ec0050918f83ea462e2.png"
    ],
    "bSaleEnabled": false,
    "sale_show_creator": false,
    "sale_sections": [],
    "sale_browsemore_text": "",
    "sale_browsemore_url": "",
    "sale_browsemore_color": "",
    "sale_browsemore_bgcolor": "",
    "localized_sale_header": [],
    "localized_sale_overlay": [],
    "localized_sale_product_banner": [],
    "localized_sale_product_mobile_banner": [],
    "localized_sale_logo": [],
    "sale_font": "",
    "sale_background_color": "",
    "sale_header_offset": 530,
    "referenced_appids": [],
    "bBroadcastEnabled": false,
    "broadcastChatSetting": "hide",
    "default_broadcast_title": "#Broadcast_default_title_dev",
    "localized_broadcast_left_image": [],
    "localized_broadcast_right_image": [],
    "broadcast_whitelist": [],
    "bScheduleEnabled": false,
    "scheduleEntries": [],
    "valve_access_log": [
      {
        "strSteamID": "76561199547417290",
        "rtUpdated": 1768973174
      },
      {
        "strSteamID": "76561198049011277",
        "rtUpdated": 1769041415
      },
      {
        "strSteamID": "76561198166130601",
        "rtUpdated": 1769035400
      }
    ],
    "clone_from_event_gid": "517481543704249946",
    "clone_from_sale_enabled": false,
    "automatically_push_updated_source": true
  },
  "announcement_body": {
    "gid": "537750912402194536",
    "clanid": "3703047",
    "posterid": "0",
    "headline": "Aggiornamento di gioco 7.40c",
    "posttime": 1769041258,
    "updatetime": 1769041415,
    "body": [
      "[p]La patch 7.40c è ora disponibile e puoi consultarne le note [url=\"https://www.dota2.com/patches/7.40c\"]qui[/url]. [/p][p][/p][p]Ti ricordiamo che l'evento Monster Hunter termina il 6 febbraio 2026, dopodiché non potrai più ottenere progressi o creare oggetti. Con l'aggiornamento di oggi, sono disponibili per l'acquisto anche i nuovi pacchetti di materiali universali, che rappresentano un metodo alternativo per ottenere materiali e creare qualsiasi oggetto ti manchi prima della conclusione dell'evento.[/p][p][/p][p]Inoltre, abbiamo risolto i seguenti problemi:  [/p][list][*][p]Risolto il problema per cui la salute aggiuntiva di Granata di Sangue non veniva aggiornata quando cambiava il numero di istanze.[/p][/*][*][p]Risolto il problema per cui Elmo del Dominatore ed Elmo del Sovrano facevano ottenere esperienza a Spirito Orso di Lone Druid invece che a Lone Druid.[/p][/*][*][p]Risolto il problema per cui Elmo del Sovrano non conferiva ricompense ed esperienza per i creep dominati.[/p][/*][*][p]Risolto il problema per cui la Runa dell'Illusione non interrompeva i proiettili all'attivazione.[/p][/*][*][p]Risolto il problema per cui il prosciugamento della salute fisico funzionava quando si attaccava un'Unità con una barriera che bloccava tutti i tipi di danno.[/p][/*][*][p]Risolto il problema per cui a volte l'acquisto rapido non rimuoveva gli oggetti in coda quando le ricette venivano combinate.[/p][/*][*][p]Risolto il problema per cui Fumo del Raggiro poteva essere utilizzato direttamente dall'inventario.[/p][/*][*][p]Risolto il problema per cui Anti-Mage con il Frammento di Aghanim e la faccetta Specchio di Magebane uccideva istantaneamente Spectre quando si utilizzava Controincantesimo mentre si camminava lungo un percorso ombroso di Pugnale spettrale indirizzato a un'altra Unità.[/p][/*][*][p]Risolto il problema per cui Tempesta doppia di Arc Warden poteva selezionare i talenti.[/p][/*][*][p]Risolto il problema per cui Bounty Hunter non poteva bersagliare Spirito Orso con Ombra alleata.[/p][/*][*][p]Risolto il problema per cui il talento di livello 25 di Brewmaster non si applicava ai guerrieri.[/p][/*][*][p]Risolto il problema per cui Brandello Infernale di Clinkz ignorava più armatura del previsto.[/p][/*][*][p]Risolto il problema per cui Condanna non acquisiva l'abilità Pietrificazione di Sciamano Predatore Antico quando divorava l'Unità neutrale.[/p][/*][*][p]Risolto il problema per cui Bis di Largo a volte non riapplicava un effetto positivo esistente su se stesso o sul bersaglio.[/p][/*][*][p]Risolto il problema per cui Morphling non perdeva il danno aggiuntivo derivante dalle pietre inutilizzate quando smetteva di replicare Earth Spirit.[/p][/*][*][p]Risolto il problema per cui Morphling generava continuamente i soldati dell'Ordine di Wukong replicando Monkey King con lo Scettro di Aghanim.[/p][/*][*][p]Risolto il problema per cui Medusa poteva ottenere salute infinita acquistando un Cuore di Tarrasque mentre Lifestealer la infestava, per poi usare Diffusione di Shadow Demon con la faccetta Promulgazione su Medusa.[/p][/*][*][p]Risolti i problemi di animazioni inattive e inattive rare dell'Arcano di Spectre.[/p][/*][/list]"
    ],
    "commentcount": 83,
    "tags": [
      "patchnotes",
      "mod_reviewed",
      "ModAct_1434573178_1769047791_0"
    ],
    "language": 3,
    "hidden": 0,
    "forum_topic_id": "684117900292851523",
    "event_gid": "537750912402194535",
    "voteupcount": 913,
    "votedowncount": 122,
    "ban_check_result": 0,
    "banned": 0
  },
  "published": 1,
  "hidden": 0,
  "rtime32_visibility_start": 0,
  "rtime32_visibility_end": 0,
  "broadcaster_accountid": 0,
  "follower_count": 0,
  "ignore_count": 0,
  "forum_topic_id": "684117900292851523",
  "rtime32_last_modified": 1769102240,
  "news_post_gid": "0",
  "rtime_mod_reviewed": 1769047792,
  "featured_app_tagid": 0,
  "referenced_appids": [],
  "build_id": 21593728,
  "build_branch": "",
  "unlisted": 0,
  "votes_up": 912,
  "votes_down": 122,
  "comment_type": "ForumTopic",
  "gidfeature": "1636418037459185108",
  "gidfeature2": "684117900292851523",
  "clan_steamid_original": "103582791433224455"
}